essential_functions/__init__.py
essential_functions/functions.py
essential_functions-0.0.1.dist-info/LICENSE
essential_functions-0.0.1.dist-info/METADATA
essential_functions-0.0.1.dist-info/WHEEL
essential_functions-0.0.1.dist-info/top_level.txt
essential_functions-0.0.1.dist-info/RECORD
