Metadata-Version: 2.1
Name: essential-functions
Version: 0.0.1
Summary: Simple package to try out packaging
Home-page: https://github.com/palnabarun/essential-functions
Author: Nabarun Pal
Author-email: pal.nabarun95@gmail.com
License: UNKNOWN
Platform: UNKNOWN
Classifier: Programming Language :: Python :: 3
Classifier: License :: OSI Approved :: MIT License
Classifier: Operating System :: OS Independent
